{
  "language": "en",
  "text": " I visited Japan last summer and saw me to food table.",
  "segments": [
    {
      "text": " I visited Japan last summer and saw me to food table.",
      "start": 0.031,
      "end": 13.463,
      "segment_words": [
        {
          "word": "I",
          "start": 0.031,
          "end": 1.494,
          "score": 0.935,
          "lang": "en"
        },
        {
          "word": "visited",
          "start": 1.515,
          "end": 2.156,
          "score": 0.832,
          "lang": "en"
        },
        {
          "word": "Japan",
          "start": 2.757,
          "end": 3.259,
          "score": 0.857,
          "lang": "en"
        },
        {
          "word": "last",
          "start": 4.381,
          "end": 4.782,
          "score": 0.692,
          "lang": "en"
        },
        {
          "word": "summer",
          "start": 4.802,
          "end": 5.143,
          "score": 0.647,
          "lang": "en"
        },
        {
          "word": "and",
          "start": 5.865,
          "end": 5.965,
          "score": 0.834,
          "lang": "en"
        },
        {
          "word": "saw",
          "start": 6.065,
          "end": 6.366,
          "score": 0.791,
          "lang": "en"
        },
        {
          "word": "me",
          "start": 6.386,
          "end": 7.048,
          "score": 0.773,
          "lang": "en"
        },
        {
          "word": "to",
          "start": 7.148,
          "end": 7.549,
          "score": 0.832,
          "lang": "en"
        },
        {
          "word": "food",
          "start": 9.754,
          "end": 10.015,
          "score": 0.677,
          "lang": "en"
        }
      ]
    }
  ],
  "words": [
    {
      "word": "I",
      "start": 0.031,
      "end": 1.494,
      "score": 0.935,
      "lang": "en"
    },
    {
      "word": "visited",
      "start": 1.515,
      "end": 2.156,
      "score": 0.832,
      "lang": "en"
    },
    {
      "word": "Japan",
      "start": 2.757,
      "end": 3.259,
      "score": 0.857,
      "lang": "en"
    },
    {
      "word": "last",
      "start": 4.381,
      "end": 4.782,
      "score": 0.692,
      "lang": "en"
    },
    {
      "word": "summer",
      "start": 4.802,
      "end": 5.143,
      "score": 0.647,
      "lang": "en"
    },
    {
      "word": "and",
      "start": 5.865,
      "end": 5.965,
      "score": 0.834,
      "lang": "en"
    },
    {
      "word": "saw",
      "start": 6.065,
      "end": 6.366,
      "score": 0.791,
      "lang": "en"
    },
    {
      "word": "me",
      "start": 6.386,
      "end": 7.048,
      "score": 0.773,
      "lang": "en"
    },
    {
      "word": "to",
      "start": 7.148,
      "end": 7.549,
      "score": 0.832,
      "lang": "en"
    },
    {
      "word": "food",
      "start": 9.754,
      "end": 10.015,
      "score": 0.677,
      "lang": "en"
    },
    {
      "word": "table.",
      "start": 11.599,
      "end": 13.483,
      "score": 0.566,
      "lang": "en"
    }
  ]
}