{
  "language": "en",
  "text": " That's what you're going on",
  "segments": [
    {
      "text": " That's what you're going on",
      "start": 0.031,
      "end": 1.82,
      "segment_words": [
        {
          "word": "That's",
          "start": 0.031,
          "end": 0.833,
          "score": 0.769,
          "lang": "en"
        },
        {
          "word": "what",
          "start": 0.854,
          "end": 1.039,
          "score": 0.39,
          "lang": "en"
        },
        {
          "word": "you're",
          "start": 1.08,
          "end": 1.203,
          "score": 0.399,
          "lang": "en"
        },
        {
          "word": "going",
          "start": 1.224,
          "end": 1.47,
          "score": 0.859,
          "lang": "en"
        }
      ]
    }
  ],
  "words": [
    {
      "word": "That's",
      "start": 0.031,
      "end": 0.833,
      "score": 0.769,
      "lang": "en"
    },
    {
      "word": "what",
      "start": 0.854,
      "end": 1.039,
      "score": 0.39,
      "lang": "en"
    },
    {
      "word": "you're",
      "start": 1.08,
      "end": 1.203,
      "score": 0.399,
      "lang": "en"
    },
    {
      "word": "going",
      "start": 1.224,
      "end": 1.47,
      "score": 0.859,
      "lang": "en"
    },
    {
      "word": "on",
      "start": 1.594,
      "end": 1.841,
      "score": 0.868,
      "lang": "en"
    }
  ]
}