{
  "language": "en",
  "text": " I enjoy eating fruits and we get to go every day.",
  "segments": [
    {
      "text": " I enjoy eating fruits and we get to go every day.",
      "start": 1.06,
      "end": 5.617,
      "segment_words": [
        {
          "word": "I",
          "start": 1.06,
          "end": 1.786,
          "score": 0.913,
          "lang": "en"
        },
        {
          "word": "enjoy",
          "start": 1.806,
          "end": 2.33,
          "score": 0.726,
          "lang": "en"
        },
        {
          "word": "eating",
          "start": 2.512,
          "end": 2.875,
          "score": 0.684,
          "lang": "en"
        },
        {
          "word": "fruits",
          "start": 3.016,
          "end": 3.359,
          "score": 0.6,
          "lang": "en"
        },
        {
          "word": "and",
          "start": 3.984,
          "end": 4.064,
          "score": 0.454,
          "lang": "en"
        },
        {
          "word": "we",
          "start": 4.206,
          "end": 4.286,
          "score": 0.387,
          "lang": "en"
        },
        {
          "word": "get",
          "start": 4.306,
          "end": 4.589,
          "score": 0.767,
          "lang": "en"
        },
        {
          "word": "to",
          "start": 4.609,
          "end": 4.649,
          "score": 0.002,
          "lang": "en"
        },
        {
          "word": "go",
          "start": 4.669,
          "end": 4.77,
          "score": 0.818,
          "lang": "en"
        },
        {
          "word": "every",
          "start": 4.851,
          "end": 5.274,
          "score": 0.332,
          "lang": "en"
        }
      ]
    }
  ],
  "words": [
    {
      "word": "I",
      "start": 1.06,
      "end": 1.786,
      "score": 0.913,
      "lang": "en"
    },
    {
      "word": "enjoy",
      "start": 1.806,
      "end": 2.33,
      "score": 0.726,
      "lang": "en"
    },
    {
      "word": "eating",
      "start": 2.512,
      "end": 2.875,
      "score": 0.684,
      "lang": "en"
    },
    {
      "word": "fruits",
      "start": 3.016,
      "end": 3.359,
      "score": 0.6,
      "lang": "en"
    },
    {
      "word": "and",
      "start": 3.984,
      "end": 4.064,
      "score": 0.454,
      "lang": "en"
    },
    {
      "word": "we",
      "start": 4.206,
      "end": 4.286,
      "score": 0.387,
      "lang": "en"
    },
    {
      "word": "get",
      "start": 4.306,
      "end": 4.589,
      "score": 0.767,
      "lang": "en"
    },
    {
      "word": "to",
      "start": 4.609,
      "end": 4.649,
      "score": 0.002,
      "lang": "en"
    },
    {
      "word": "go",
      "start": 4.669,
      "end": 4.77,
      "score": 0.818,
      "lang": "en"
    },
    {
      "word": "every",
      "start": 4.851,
      "end": 5.274,
      "score": 0.332,
      "lang": "en"
    },
    {
      "word": "day.",
      "start": 5.557,
      "end": 5.637,
      "score": 0.25,
      "lang": "en"
    }
  ]
}