{
  "language": "en",
  "text": " West, West, West, West, West, West, West, West, West. Data south, data.",
  "segments": [
    {
      "text": " West, West, West, West, West, West, West, West, West. Data south, data.",
      "start": 0.875,
      "end": 14.611,
      "segment_words": [
        {
          "word": "West,",
          "start": 0.875,
          "end": 1.477,
          "score": 0.887,
          "lang": "en"
        },
        {
          "word": "West,",
          "start": 2.562,
          "end": 2.883,
          "score": 0.639,
          "lang": "en"
        },
        {
          "word": "West,",
          "start": 3.827,
          "end": 4.189,
          "score": 0.679,
          "lang": "en"
        },
        {
          "word": "West,",
          "start": 4.972,
          "end": 5.293,
          "score": 0.669,
          "lang": "en"
        },
        {
          "word": "West,",
          "start": 6.518,
          "end": 7.843,
          "score": 0.509,
          "lang": "en"
        },
        {
          "word": "West,",
          "start": 7.863,
          "end": 9.952,
          "score": 0.532,
          "lang": "en"
        },
        {
          "word": "West,",
          "start": 9.972,
          "end": 10.936,
          "score": 0.647,
          "lang": "en"
        },
        {
          "word": "West,",
          "start": 10.956,
          "end": 12.201,
          "score": 0.788,
          "lang": "en"
        },
        {
          "word": "West.",
          "start": 12.221,
          "end": 12.663,
          "score": 0.813,
          "lang": "en"
        },
        {
          "word": "Data",
          "start": 12.683,
          "end": 12.884,
          "score": 0.334,
          "lang": "en"
        },
        {
          "word": "south,",
          "start": 12.904,
          "end": 13.968,
          "score": 0.667,
          "lang": "en"
        }
      ]
    }
  ],
  "words": [
    {
      "word": "West,",
      "start": 0.875,
      "end": 1.477,
      "score": 0.887,
      "lang": "en"
    },
    {
      "word": "West,",
      "start": 2.562,
      "end": 2.883,
      "score": 0.639,
      "lang": "en"
    },
    {
      "word": "West,",
      "start": 3.827,
      "end": 4.189,
      "score": 0.679,
      "lang": "en"
    },
    {
      "word": "West,",
      "start": 4.972,
      "end": 5.293,
      "score": 0.669,
      "lang": "en"
    },
    {
      "word": "West,",
      "start": 6.518,
      "end": 7.843,
      "score": 0.509,
      "lang": "en"
    },
    {
      "word": "West,",
      "start": 7.863,
      "end": 9.952,
      "score": 0.532,
      "lang": "en"
    },
    {
      "word": "West,",
      "start": 9.972,
      "end": 10.936,
      "score": 0.647,
      "lang": "en"
    },
    {
      "word": "West,",
      "start": 10.956,
      "end": 12.201,
      "score": 0.788,
      "lang": "en"
    },
    {
      "word": "West.",
      "start": 12.221,
      "end": 12.663,
      "score": 0.813,
      "lang": "en"
    },
    {
      "word": "Data",
      "start": 12.683,
      "end": 12.884,
      "score": 0.334,
      "lang": "en"
    },
    {
      "word": "south,",
      "start": 12.904,
      "end": 13.968,
      "score": 0.667,
      "lang": "en"
    },
    {
      "word": "data.",
      "start": 13.988,
      "end": 14.631,
      "score": 0.855,
      "lang": "en"
    }
  ]
}