{
  "language": "en",
  "text": " the land.",
  "segments": [
    {
      "text": " the land.",
      "start": 0.031,
      "end": 1.347,
      "segment_words": [
        {
          "word": "the",
          "start": 0.031,
          "end": 0.303,
          "score": 0.615,
          "lang": "en"
        }
      ]
    }
  ],
  "words": [
    {
      "word": "the",
      "start": 0.031,
      "end": 0.303,
      "score": 0.615,
      "lang": "en"
    },
    {
      "word": "land.",
      "start": 0.386,
      "end": 1.368,
      "score": 0.536,
      "lang": "en"
    }
  ]
}