{
  "language": "en",
  "text": " Okay, what's your name?",
  "segments": [
    {
      "text": " Okay, what's your name?",
      "start": 1.702,
      "end": 4.283,
      "segment_words": [
        {
          "word": "Okay,",
          "start": 1.702,
          "end": 3.197,
          "score": 0.862,
          "lang": "en"
        },
        {
          "word": "what's",
          "start": 3.218,
          "end": 3.464,
          "score": 0.943,
          "lang": "en"
        },
        {
          "word": "your",
          "start": 3.505,
          "end": 3.648,
          "score": 0.882,
          "lang": "en"
        }
      ]
    }
  ],
  "words": [
    {
      "word": "Okay,",
      "start": 1.702,
      "end": 3.197,
      "score": 0.862,
      "lang": "en"
    },
    {
      "word": "what's",
      "start": 3.218,
      "end": 3.464,
      "score": 0.943,
      "lang": "en"
    },
    {
      "word": "your",
      "start": 3.505,
      "end": 3.648,
      "score": 0.882,
      "lang": "en"
    },
    {
      "word": "name?",
      "start": 3.689,
      "end": 4.303,
      "score": 0.919,
      "lang": "en"
    }
  ]
}