{
  "language": "en",
  "text": " Thank you.",
  "segments": [
    {
      "text": " Thank you.",
      "start": 1.702,
      "end": 17.48,
      "segment_words": [
        {
          "word": "Thank",
          "start": 1.702,
          "end": 7.503,
          "score": 0.477,
          "lang": "en"
        }
      ]
    }
  ],
  "words": [
    {
      "word": "Thank",
      "start": 1.702,
      "end": 7.503,
      "score": 0.477,
      "lang": "en"
    },
    {
      "word": "you.",
      "start": 11.378,
      "end": 17.5,
      "score": 0.615,
      "lang": "en"
    }
  ]
}